channels_simplify/__init__.py
channels_simplify/consumers.py
channels_simplify/decoratos.py
channels_simplify/signatures.py
channels_simplify/utils.py
channels_simplify-0.1.0.5.dist-info/LICENSE
channels_simplify-0.1.0.5.dist-info/METADATA
channels_simplify-0.1.0.5.dist-info/WHEEL
channels_simplify-0.1.0.5.dist-info/top_level.txt
channels_simplify-0.1.0.5.dist-info/RECORD
